manifestoo/__init__.py
manifestoo/__main__.py
manifestoo/addon_sorter.py
manifestoo/addons_path.py
manifestoo/addons_selection.py
manifestoo/dependency_iterator.py
manifestoo/echo.py
manifestoo/exceptions.py
manifestoo/license.py
manifestoo/main.py
manifestoo/options.py
manifestoo/utils.py
manifestoo/version.py
manifestoo/commands/__init__.py
manifestoo/commands/check_dev_status.py
manifestoo/commands/check_licenses.py
manifestoo/commands/interactive_tree.py
manifestoo/commands/list.py
manifestoo/commands/list_codepends.py
manifestoo/commands/list_depends.py
manifestoo/commands/list_external_dependencies.py
manifestoo/commands/tree.py
manifestoo-1.1.dist-info/METADATA
manifestoo-1.1.dist-info/WHEEL
manifestoo-1.1.dist-info/entry_points.txt
manifestoo-1.1.dist-info/licenses/LICENSE
manifestoo-1.1.dist-info/RECORD
