Metadata-Version: 2.4
Name: manifestoo
Version: 1.1
Summary: A tool to reason about Odoo addons manifests
Project-URL: Homepage, https://github.com/acsone/manifestoo
Project-URL: Documentation, https://manifestoo.readthedocs.io/en/stable/
Project-URL: Changelog, https://manifestoo.readthedocs.io/en/stable/changelog.html
Project-URL: Source, https://github.com/acsone/manifestoo
Author-email: Stéphane Bidoul <stephane.bidoul@acsone.eu>
License-File: LICENSE
Classifier: Development Status :: 4 - Beta
Classifier: Framework :: Odoo
Classifier: Intended Audience :: Developers
Classifier: License :: OSI Approved :: MIT License
Classifier: Operating System :: OS Independent
Classifier: Programming Language :: Python
Classifier: Programming Language :: Python :: 3
Classifier: Programming Language :: Python :: 3 :: Only
Requires-Python: >=3.7
Requires-Dist: importlib-metadata; python_version < '3.8'
Requires-Dist: manifestoo-core>=0.8
Requires-Dist: textual>=0.6
Requires-Dist: typer>=0.12.1
Provides-Extra: dev
Requires-Dist: textual[dev]; extra == 'dev'
Provides-Extra: doc
Requires-Dist: furo; extra == 'doc'
Requires-Dist: myst-parser; extra == 'doc'
Requires-Dist: sphinx; extra == 'doc'
Requires-Dist: sphinxcontrib-towncrier; extra == 'doc'
Requires-Dist: towncrier; extra == 'doc'
Provides-Extra: test
Requires-Dist: coverage[toml]; extra == 'test'
Requires-Dist: pytest; extra == 'test'
